dunsync/__init__.py
dunsync/unsync.py
dunsync-0.1.1.dist-info/LICENSE
dunsync-0.1.1.dist-info/WHEEL
dunsync-0.1.1.dist-info/METADATA
dunsync-0.1.1.dist-info/RECORD
