Metadata-Version: 2.1
Name: dunsync
Version: 0.1.1
Summary: Identical to unsync, but supports cpu-bound continuation functions
Home-page: https://github.com/danhje/dunsync
License: MIT
Keywords: unsync,asyncio,threading,multiprocessing,chaining,continuation
Author: Daniel Hjertholm
Requires-Python: >=3.8,<4.0
Classifier: Development Status :: 4 - Beta
Classifier: Intended Audience :: Developers
Classifier: License :: OSI Approved :: MIT License
Classifier: Natural Language :: English
Classifier: Operating System :: OS Independent
Classifier: Programming Language :: Python
Classifier: Programming Language :: Python :: 3
Classifier: Programming Language :: Python :: 3.10
Classifier: Programming Language :: Python :: 3.8
Classifier: Programming Language :: Python :: 3.9
Classifier: Topic :: Software Development :: Libraries
Classifier: Topic :: Software Development :: Libraries :: Python Modules
Project-URL: Repository, https://github.com/danhje/dunsync
